flockserve/__init__.py
flockserve/autoscaler.py
flockserve/cli.py
flockserve/config.py
flockserve/flockserve.py
flockserve/flockserve_app.py
flockserve/flockserve_app_bu.py
flockserve/flockserve_app_tmp.py
flockserve/flockserver.py
flockserve/loadbalancer.py
flockserve/run.py
flockserve/telemetry.py
flockserve/utils.py
flockserve/worker_handler.py
flockserve/worker_manager.py
flockserve/workermanager.py
flockserve-0.1.3.dist-info/AUTHORS.md
flockserve-0.1.3.dist-info/LICENSE
flockserve-0.1.3.dist-info/METADATA
flockserve-0.1.3.dist-info/WHEEL
flockserve-0.1.3.dist-info/entry_points.txt
flockserve-0.1.3.dist-info/top_level.txt
flockserve-0.1.3.dist-info/RECORD
