Metadata-Version: 2.1
Name: flockserve
Version: 0.1.3
Summary: Open-source Sky Computing Inference Endpoint
Home-page: https://github.com/jdooodle/flockserve
Author: Antti Puurula, Anil Gurbuz
License: Apache Software License 2.0
Keywords: flockserve
Classifier: Development Status :: 2 - Pre-Alpha
Classifier: Intended Audience :: Developers
Classifier: License :: OSI Approved :: Apache Software License
Classifier: Natural Language :: English
Classifier: Programming Language :: Python :: 3.7
Classifier: Programming Language :: Python :: 3.8
Classifier: Programming Language :: Python :: 3.9
Classifier: Programming Language :: Python :: 3.10
Classifier: Programming Language :: Python :: 3.11
Requires-Python: >=3.7, <3.12
License-File: LICENSE
License-File: AUTHORS.md
Requires-Dist: skypilot[all]
Requires-Dist: opentelemetry-api
Requires-Dist: opentelemetry-instrumentation
Requires-Dist: opentelemetry-sdk
Requires-Dist: fastapi
Requires-Dist: opentelemetry-instrumentation-fastapi
Requires-Dist: uvicorn
Requires-Dist: fire
